onto_vae/__init__.py
onto_vae/data/gene_term_mapping.txt
onto_vae/data/pbmc_sample_annot.csv
onto_vae/data/pbmc_sample_expr.csv
onto_vae/data/pw.obo
onto_vae/fast_data_loader.py
onto_vae/modules.py
onto_vae/ontobj.py
onto_vae/utils.py
onto_vae/vae_model.py
onto_vae-0.1.0.dist-info/LICENSE
onto_vae-0.1.0.dist-info/WHEEL
onto_vae-0.1.0.dist-info/METADATA
onto_vae-0.1.0.dist-info/RECORD
