Metadata-Version: 2.1
Name: onto-vae
Version: 0.1.0
Summary: Package to preprocess ontologies, train OntoVAE models and obtain pathway activities.
Home-page: https://github.com/hdsu-bioquant/onto-vae
License: GPLv3
Author: daria-dc
Author-email: daria.doncevic@gmail.com
Requires-Python: >=3.7,<4.0
Classifier: License :: Other/Proprietary License
Classifier: Programming Language :: Python :: 3
Classifier: Programming Language :: Python :: 3.7
Classifier: Programming Language :: Python :: 3.8
Classifier: Programming Language :: Python :: 3.9
Classifier: Programming Language :: Python :: 3.10
Classifier: Programming Language :: Python :: 3.11
Requires-Dist: colorcet (>=3.0.0)
Requires-Dist: goatools (>=1.0.15)
Requires-Dist: pandas (>=1.1.0)
Requires-Dist: seaborn (>=0.11.0)
Requires-Dist: torch (>=1.10.0)
Requires-Dist: tqdm (>=4.60.0)
Project-URL: Repository, https://github.com/hdsu-bioquant/onto-vae
